pypore3d/p3dFiltPy_16.py
pypore3d/p3dFiltPy.py
pypore3d/p3dSkelPy.py
pypore3d/p3d_SITK_read_raw.py
pypore3d/p3d_common_lib.py
pypore3d/p3dSITKPy_16.py
pypore3d/_p3dBlob.cpython-38-x86_64-linux-gnu.so
pypore3d/__init__.py
pypore3d/p3d_SITK_common_lib.py
pypore3d/_p3dFilt.cpython-38-x86_64-linux-gnu.so
pypore3d/p3dBlob.py
pypore3d/_p3dSkel.cpython-38-x86_64-linux-gnu.so
pypore3d/p3d_SITK_common_lib_16.py
pypore3d/p3dBlobPy.py
pypore3d/p3dSkel.py
pypore3d/p3dSITKPy.py
pypore3d/p3dFilt.py
p3dpkg_with_16bit/p3dFiltPy.py
p3dpkg_with_16bit/p3dSkelPy.py
p3dpkg_with_16bit/p3d_SITK_read_raw.py
p3dpkg_with_16bit/p3d_common_lib.py
p3dpkg_with_16bit/p3dSITKPy_16bit.py
p3dpkg_with_16bit/__init__.py
p3dpkg_with_16bit/p3dFiltPy_16bit.py
p3dpkg_with_16bit/p3d_SITK_common_lib.py
p3dpkg_with_16bit/p3dBlob.py
p3dpkg_with_16bit/p3d_SITK_common_lib_16bit.py
p3dpkg_with_16bit/p3dBlobPy.py
p3dpkg_with_16bit/p3dSkel.py
p3dpkg_with_16bit/p3dSITKPy.py
p3dpkg_with_16bit/p3dFilt.py
pypore3d-0.0.1.dist-info/METADATA
pypore3d-0.0.1.dist-info/LICENSE
pypore3d-0.0.1.dist-info/top_level.txt
pypore3d-0.0.1.dist-info/WHEEL
pypore3d-0.0.1.dist-info/RECORD
