Metadata-Version: 2.1
Name: pypore3d
Version: 0.0.1
Summary: Pore3d with python wrappers
Home-page: https://gitlab.elettra.eu/amal.abouelhassan/pore3d_py
Author: Amal Aboulhassan
Author-email: aboulhassan.amal@gmail.com
License: UNKNOWN
Platform: UNKNOWN
Classifier: Programming Language :: Python :: 3
Classifier: License :: OSI Approved :: MIT License
Classifier: Operating System :: OS Independent
License-File: LICENSE
